fooddatacentral/__init__.py
fooddatacentral/fooddatacentral.py
tests/__init__.py
tests/test_ingredients.py
tests/test_nutrients.py
tests/test_search.py
fooddatacentral-1.0.10.dist-info/LICENSE.txt
fooddatacentral-1.0.10.dist-info/METADATA
fooddatacentral-1.0.10.dist-info/WHEEL
fooddatacentral-1.0.10.dist-info/top_level.txt
fooddatacentral-1.0.10.dist-info/RECORD
