Metadata-Version: 2.1
Name: fooddatacentral
Version: 1.0.10
Summary: Python module to obtain information from the USDA's Food Data Central data project.
Home-page: https://github.com/ligon/fooddatacentral
Author-email: ligon@berkeley.edu
License: Creative Commons Attribution-NonCommercial-ShareAlike 4.0. http://creativecommons.org/licenses/by-nc-sa/4.0/
Keywords: USDA,FDC
Classifier: Intended Audience :: Developers
Classifier: Programming Language :: Python :: 3 :: Only
License-File: LICENSE.txt
